fastlogging-0.9.6.dist-info/RECORD
fastlogging-0.9.6.dist-info/METADATA
fastlogging-0.9.6.dist-info/WHEEL
fastlogging-0.9.6.dist-info/LICENSE.txt
fastlogging-0.9.6.dist-info/top_level.txt
fastlogging/__init__.py
fastlogging/optimize.py
fastlogging/network.cpython-36m-x86_64-linux-gnu.so
fastlogging/fastlogging.cpython-36m-x86_64-linux-gnu.so
fastlogging/console.py
