Metadata-Version: 2.1
Name: fastlogging
Version: 0.9.6
Summary: A faster replacement of the standard logging module.
Home-page: https://github.com/brmmm3/fastlogging
Author: Martin Bammer
Author-email: mrbm74@gmail.com
License: MIT
Download-URL: https://github.com/brmmm3/fastlogging/releases/download/0.9.6/fastlogging-0.9.6.tar.gz
Keywords: fast logging
Platform: UNKNOWN
Classifier: Development Status :: 4 - Beta
Classifier: Intended Audience :: Developers
Classifier: Topic :: Software Development :: Build Tools
Classifier: License :: OSI Approved :: MIT License
Classifier: Operating System :: OS Independent
Classifier: Programming Language :: Python :: 2
Classifier: Programming Language :: Python :: 2.7
Classifier: Programming Language :: Python :: 3
Classifier: Programming Language :: Python :: 3.4
Classifier: Programming Language :: Python :: 3.5
Classifier: Programming Language :: Python :: 3.6
Classifier: Programming Language :: Python :: 3.7
Classifier: Programming Language :: Python :: 3.8
